master_ssh-2.0.8.1.data/scripts/master-ssh
masterssh/__init__.py
masterssh/masterssh.py
master_ssh-2.0.8.1.dist-info/LICENSE.md
master_ssh-2.0.8.1.dist-info/METADATA
master_ssh-2.0.8.1.dist-info/WHEEL
master_ssh-2.0.8.1.dist-info/top_level.txt
master_ssh-2.0.8.1.dist-info/RECORD
