Metadata-Version: 2.1
Name: master-ssh
Version: 2.0.8.1
Summary: Tool to connect to multiple SSH servers and broadcast commands.
Home-page: https://github.com/JaanPorkon/master-ssh
Author: Jaan Porkon
Author-email: jaantrill@gmail.com
License: UNKNOWN
Platform: UNKNOWN
Classifier: Programming Language :: Python :: 3
Classifier: License :: OSI Approved :: MIT License
Classifier: Operating System :: OS Independent
Requires-Python: >=3.6
Requires-Dist: requests
Requires-Dist: paramiko
Requires-Dist: configparser
Requires-Dist: termcolor
